ttm214_async/__init__.py
ttm214_async/device.py
ttm214_async/errors.py
ttm214_async/messages.py
ttm214_async-0.2.0.dist-info/LICENSE
ttm214_async-0.2.0.dist-info/METADATA
ttm214_async-0.2.0.dist-info/WHEEL
ttm214_async-0.2.0.dist-info/top_level.txt
ttm214_async-0.2.0.dist-info/RECORD
