Metadata-Version: 2.1
Name: ttm214-async
Version: 0.2.0
Summary: TTM214 device control library
Home-page: https://github.com/mochi534/TTM214_async
Author: mochi534
Author-email: lib654852@gmail.com
Maintainer: mochi534
Maintainer-email: lib654852@gmail.com
License: MIT
Classifier: Development Status :: 3 - Alpha
Classifier: Intended Audience :: Developers
Classifier: License :: OSI Approved :: MIT License
Classifier: Programming Language :: Python
Classifier: Programming Language :: Python :: 3
Classifier: Programming Language :: Python :: 3.11
Requires-Python: >=3.11
License-File: LICENSE
Requires-Dist: pyserial>=3.5
Requires-Dist: pyserial-asyncio>=0.6
